setup.py
sorty.py
Sorty.egg-info/PKG-INFO
Sorty.egg-info/SOURCES.txt
Sorty.egg-info/dependency_links.txt
Sorty.egg-info/entry_points.txt
Sorty.egg-info/requires.txt
Sorty.egg-info/top_level.txt