Metadata-Version: 1.1
Name: Sorty
Version: 1.0.0
Summary: A File Sorting Magician for your PC built in Python
Home-page: https://github.com/geekpradd/Sorty
Author: Pradipta Bora
Author-email: pradd@outlook.com
License: MIT
Keywords: files sort utility
Platform: UNKNOWN
Classifier: Development Status :: 5 - Production/Stable
Classifier: Topic :: Utilities
Classifier: License :: OSI Approved :: MIT License
Classifier: Operating System :: OS Independent
Classifier: Programming Language :: Python
